README.md
setup.py
OkReport.egg-info/PKG-INFO
OkReport.egg-info/SOURCES.txt
OkReport.egg-info/dependency_links.txt
OkReport.egg-info/entry_points.txt
OkReport.egg-info/requires.txt
OkReport.egg-info/top_level.txt
okreport/__init__.py
okreport/apk_parser.py
okreport/chart.py
okreport/config.py
okreport/coverage_parser.py
okreport/findbugs_parser.py
okreport/helper.py
okreport/html.py
okreport/lint_parser.py
okreport/pmd_parser.py
okreport/qark_parser.py
okreport/report.py
okreport/sender.py