Metadata-Version: 1.1
Name: OkReport
Version: 0.1.5
Summary: This tool is used for assembling report from okcheck and send to mails
Home-page: https://github.com/lingochamp/okreport
Author: Jacksgong
Author-email: igzhenjie@gmail.com
License: Apache2
Keywords: okreport okcheck
Platform: UNKNOWN
Classifier: Development Status :: 5 - Production/Stable
Classifier: License :: OSI Approved :: Apache Software License
Classifier: Programming Language :: Python :: 2.7
Classifier: Programming Language :: Python :: 3
Classifier: Programming Language :: Python :: 3.3
Classifier: Programming Language :: Python :: 3.4
Classifier: Programming Language :: Python :: 3.5
Classifier: Programming Language :: Python :: 3.6
